biketrauma/__init__.py
biketrauma/io/Load_db.py
biketrauma/io/__init__.py
biketrauma/preprocess/__init__.py
biketrauma/preprocess/get_accident.py
biketrauma/vis/__init__.py
biketrauma/vis/plot_location.py
biketrauma_AV-0.0.1.dist-info/METADATA
biketrauma_AV-0.0.1.dist-info/WHEEL
biketrauma_AV-0.0.1.dist-info/top_level.txt
biketrauma_AV-0.0.1.dist-info/RECORD
