Metadata-Version: 2.1
Name: biketrauma-AV
Version: 0.0.1
Summary: Visualization of a bicycle accident db
Home-page: http://github.com/AmelieVernay.git
Author: AmelieVernay
Author-email: amelie.vernay@etu.umontpellier.fr
License: MIT
Platform: UNKNOWN
